syft_code_queue/__init__.py
syft_code_queue/client.py
syft_code_queue/models.py
syft_code_queue-0.1.27.dist-info/METADATA
syft_code_queue-0.1.27.dist-info/WHEEL
syft_code_queue-0.1.27.dist-info/entry_points.txt
syft_code_queue-0.1.27.dist-info/RECORD
