Metadata-Version: 2.4
Name: syft-code-queue
Version: 0.1.27
Summary: Job submission and approval workflow for SyftBox (execution handled by syft-simple-runner)
Project-URL: Homepage, https://github.com/OpenMined/syft-code-queue
Project-URL: Repository, https://github.com/OpenMined/syft-code-queue.git
Project-URL: Issues, https://github.com/OpenMined/syft-code-queue/issues
Author-email: OpenMined <info@openmined.org>
License: Apache-2.0
Classifier: Development Status :: 3 - Alpha
Classifier: Intended Audience :: Developers
Classifier: License :: OSI Approved :: Apache Software License
Classifier: Programming Language :: Python :: 3
Classifier: Programming Language :: Python :: 3.12
Requires-Python: >=3.9
Requires-Dist: click>=8.0.0
Requires-Dist: fastapi>=0.104.0
Requires-Dist: loguru>=0.7.0
Requires-Dist: pathlib
Requires-Dist: pydantic>=2.0.0
Requires-Dist: python-multipart>=0.0.6
Requires-Dist: syft-core
Requires-Dist: syft-perm>=0.1.0
Requires-Dist: tabulate>=0.9.0
Requires-Dist: uvicorn[standard]>=0.24.0
Provides-Extra: dev
Requires-Dist: build; extra == 'dev'
Requires-Dist: pytest-cov; extra == 'dev'
Requires-Dist: pytest>=7.0.0; extra == 'dev'
Requires-Dist: ruff; extra == 'dev'
Requires-Dist: twine; extra == 'dev'
